ezconda/__init__.py
ezconda/__main__.py
ezconda/_utils.py
ezconda/config.py
ezconda/console.py
ezconda/create.py
ezconda/experimental/__init__.py
ezconda/experimental/lock.py
ezconda/files/__init__.py
ezconda/files/lockfile.py
ezconda/install.py
ezconda/main.py
ezconda/remove.py
ezconda/solver.py
ezconda/summary.py
ezconda/sync.py
ezconda/update.py
ezconda-0.8.0.dist-info/entry_points.txt
ezconda-0.8.0.dist-info/LICENSE
ezconda-0.8.0.dist-info/WHEEL
ezconda-0.8.0.dist-info/METADATA
ezconda-0.8.0.dist-info/RECORD
