Metadata-Version: 2.1
Name: ezconda
Version: 0.8.0
Summary: Create, Manage, Re-create conda environments & specifications with ease.
Author: Sarthak Jariwala
Requires-Python: >=3.7,<4.0
Classifier: Programming Language :: Python :: 3
Classifier: Programming Language :: Python :: 3.10
Classifier: Programming Language :: Python :: 3.7
Classifier: Programming Language :: Python :: 3.8
Classifier: Programming Language :: Python :: 3.9
Requires-Dist: PyYAML (>=5.4.1)
Requires-Dist: importlib-metadata (>=4.11.4,<5.0.0)
Requires-Dist: rich (>=10.11.0)
Requires-Dist: tomlkit (>=0.9.0)
Requires-Dist: typer[all] (>=0.4.0)
